harmony_toolbox-1.4.0.dist-info/licenses/LICENSE
toolbox/__init__.py
toolbox/cli.py
toolbox/config.py
toolbox/toolbox.py
toolbox/utils.py
harmony_toolbox-1.4.0.dist-info/METADATA
harmony_toolbox-1.4.0.dist-info/WHEEL
harmony_toolbox-1.4.0.dist-info/top_level.txt
harmony_toolbox-1.4.0.dist-info/RECORD
