Metadata-Version: 2.4
Name: harmony-toolbox
Version: 1.4.0
Summary: Harmony ONE Validator Node Toolbox and Easy Setup
Home-page: https://github.com/easy-node-pro/harmony-toolbox
Author: EasyNodePro.com
Author-email: support@easynodepro.com
Project-URL: Bug Tracker, https://github.com/easy-node-pro/harmony-toolbox/issues
Project-URL: repository, https://github.com/easy-node-pro/harmony-toolbox
Classifier: Programming Language :: Python :: 3
Classifier: License :: OSI Approved :: MIT License
Classifier: Operating System :: OS Independent
Requires-Python: >=3.6
License-File: LICENSE
Dynamic: license-file
